makefile_creator/__init__.py
makefile_creator/__main__.py
makefile_creator/args.py
makefile_creator/collection.py
makefile_creator/config.py
makefile_creator/file_util.py
makefile_creator/iset.py
makefile_creator/makefiles.py
makefile_creator/test.py
makefile_creator/util.py
makefile_creator/utils.py
makefile_creator-1.0.0.dist-info/LICENSE
makefile_creator-1.0.0.dist-info/METADATA
makefile_creator-1.0.0.dist-info/WHEEL
makefile_creator-1.0.0.dist-info/top_level.txt
makefile_creator-1.0.0.dist-info/RECORD
