Metadata-Version: 2.1
Name: makefile-creator
Version: 1.0.0
Summary: MakeFile-Creator for makefiles management in C/C++ projects.
Home-page: https://github.com/m3sserschmitt/MakeFile-Creator.git
Author: Romulus-Emanuel Ruja
Author-email: romulus-emanuel.ruja@tutanota.com
License: MIT License
Platform: Linux
Classifier: Development Status :: 4 - Beta
Classifier: Environment :: Console
Classifier: Intended Audience :: Developers
Classifier: Operating System :: POSIX :: Linux
Classifier: Programming Language :: Python :: 3
Classifier: Programming Language :: Python :: 3.6
Classifier: Programming Language :: Python :: 3.7
Classifier: Programming Language :: Python :: 3.8
Classifier: Programming Language :: Python :: 3.9
Classifier: License :: OSI Approved :: MIT License
Classifier: Natural Language :: English
Requires-Python: >=3.6
